{"_id":{"film_id":"HO00001379","cinema_id":"555"},"file":[{"_id":"6109a6173501a660f792f8c0","cinema_name":"Wimbledon","showtimeId":"555-5405","film_id":"HO00001379","cinema_id":"555","film_name":"The Suicide Squad","date":"2021-08-04","time":"2021-08-04T10:00:00+01:00","is3d":false,"__v":0},{"_id":"6109a6173501a660f792f8c1","cinema_name":"Wimbledon","showtimeId":"555-5474","film_id":"HO00001379","cinema_id":"555","film_name":"The Suicide Squad","date":"2021-08-04","time":"2021-08-04T10:11:00+01:00","is3d":false,"__v":0},{"_id":"6109a6173501a660f792f8c2","cinema_name":"Wimbledon","showtimeId":"555-5483","film_id":"HO00001379","cinema_id":"555","film_name":"The Suicide Squad","date":"2021-08-04","time":"2021-08-04T10:20:00+01:00","is3d":false,"__v":0},{"_id":"6109a6173501a660f792f8c3","cinema_name":"Wimbledon","showtimeId":"555-5425","film_id":"HO00001379","cinema_id":"555","film_name":"The Suicide Squad","date":"2021-08-04","time":"2021-08-04T10:30:00+01:00","is3d":false,"__v":0},{"_id":"6109a6173501a660f792f8c4","cinema_name":"Wimbledon","showtimeId":"555-5439","film_id":"HO00001379","cinema_id":"555","film_name":"The Suicide Squad","date":"2021-08-04","time":"2021-08-04T10:50:00+01:00","is3d":false,"__v":0},{"_id":"6109a6173501a660f792f8c5","cinema_name":"Wimbledon","showtimeId":"555-5408","film_id":"HO00001379","cinema_id":"555","film_name":"The Suicide Squad","date":"2021-08-04","time":"2021-08-04T10:50:00+01:00","is3d":false,"__v":0},{"_id":"6109a6173501a660f792f8c6","cinema_name":"Wimbledon","showtimeId":"555-5487","film_id":"HO00001379","cinema_id":"555","film_name":"The Suicide Squad","date":"2021-08-04","time":"2021-08-04T11:00:00+01:00","is3d":false,"__v":0},{"_id":"6109a6173501a660f792f8c7","cinema_name":"Wimbledon","showtimeId":"555-5435","film_id":"HO00001379","cinema_id":"555","film_name":"The Suicide Squad","date":"2021-08-04","time":"2021-08-04T11:10:00+01:00","is3d":false,"__v":0},{"_id":"6109a6173501a660f792f8c8","cinema_name":"Wimbledon","showtimeId":"555-5407","film_id":"HO00001379","cinema_id":"555","film_name":"The Suicide Squad","date":"2021-08-04","time":"2021-08-04T11:30:00+01:00","is3d":false,"__v":0},{"_id":"6109a6173501a660f792f8c9","cinema_name":"Wimbledon","showtimeId":"555-5395","film_id":"HO00001379","cinema_id":"555","film_name":"The Suicide Squad","date":"2021-08-04","time":"2021-08-04T12:00:00+01:00","is3d":false,"__v":0},{"_id":"6109a6173501a660f792f8ca","cinema_name":"Wimbledon","showtimeId":"555-5422","film_id":"HO00001379","cinema_id":"555","film_name":"The Suicide Squad","date":"2021-08-04","time":"2021-08-04T12:00:00+01:00","is3d":false,"__v":0},{"_id":"6109a6173501a660f792f8cb","cinema_name":"Wimbledon","showtimeId":"555-5477","film_id":"HO00001379","cinema_id":"555","film_name":"The Suicide Squad","date":"2021-08-04","time":"2021-08-04T12:10:00+01:00","is3d":false,"__v":0},{"_id":"6109a6173501a660f792f8cc","cinema_name":"Wimbledon","showtimeId":"555-5433","film_id":"HO00001379","cinema_id":"555","film_name":"The Suicide Squad","date":"2021-08-04","time":"2021-08-04T12:20:00+01:00","is3d":false,"__v":0},{"_id":"6109a6173501a660f792f8cd","cinema_name":"Wimbledon","showtimeId":"555-5426","film_id":"HO00001379","cinema_id":"555","film_name":"The Suicide Squad","date":"2021-08-04","time":"2021-08-04T13:00:00+01:00","is3d":false,"__v":0},{"_id":"6109a6173501a660f792f8ce","cinema_name":"Wimbledon","showtimeId":"555-5475","film_id":"HO00001379","cinema_id":"555","film_name":"The Suicide Squad","date":"2021-08-04","time":"2021-08-04T13:10:00+01:00","is3d":false,"__v":0},{"_id":"6109a6173501a660f792f8cf","cinema_name":"Wimbledon","showtimeId":"555-5448","film_id":"HO00001379","cinema_id":"555","film_name":"The Suicide Squad","date":"2021-08-04","time":"2021-08-04T13:20:00+01:00","is3d":false,"__v":0},{"_id":"6109a6173501a660f792f8d0","cinema_name":"Wimbledon","showtimeId":"555-5467","film_id":"HO00001379","cinema_id":"555","film_name":"The Suicide Squad","date":"2021-08-04","time":"2021-08-04T13:30:00+01:00","is3d":false,"__v":0},{"_id":"6109a6173501a660f792f8d1","cinema_name":"Wimbledon","showtimeId":"555-5418","film_id":"HO00001379","cinema_id":"555","film_name":"The Suicide Squad","date":"2021-08-04","time":"2021-08-04T13:50:00+01:00","is3d":false,"__v":0},{"_id":"6109a6173501a660f792f8d2","cinema_name":"Wimbledon","showtimeId":"555-5401","film_id":"HO00001379","cinema_id":"555","film_name":"The Suicide Squad","date":"2021-08-04","time":"2021-08-04T14:00:00+01:00","is3d":false,"__v":0},{"_id":"6109a6173501a660f792f8d3","cinema_name":"Wimbledon","showtimeId":"555-5446","film_id":"HO00001379","cinema_id":"555","film_name":"The Suicide Squad","date":"2021-08-04","time":"2021-08-04T14:10:00+01:00","is3d":false,"__v":0},{"_id":"6109a6173501a660f792f8d4","cinema_name":"Wimbledon","showtimeId":"555-5444","film_id":"HO00001379","cinema_id":"555","film_name":"The Suicide Squad","date":"2021-08-04","time":"2021-08-04T14:20:00+01:00","is3d":false,"__v":0},{"_id":"6109a6173501a660f792f8d5","cinema_name":"Wimbledon","showtimeId":"555-5394","film_id":"HO00001379","cinema_id":"555","film_name":"The Suicide Squad","date":"2021-08-04","time":"2021-08-04T14:30:00+01:00","is3d":false,"__v":0},{"_id":"6109a6173501a660f792f8d6","cinema_name":"Wimbledon","showtimeId":"555-5423","film_id":"HO00001379","cinema_id":"555","film_name":"The Suicide Squad","date":"2021-08-04","time":"2021-08-04T14:50:00+01:00","is3d":false,"__v":0},{"_id":"6109a6173501a660f792f8d7","cinema_name":"Wimbledon","showtimeId":"555-3902","film_id":"HO00001379","cinema_id":"555","film_name":"The Suicide Squad","date":"2021-08-04","time":"2021-08-04T15:25:00+01:00","is3d":false,"__v":0},{"_id":"6109a6173501a660f792f8d8","cinema_name":"Wimbledon","showtimeId":"555-5427","film_id":"HO00001379","cinema_id":"555","film_name":"The Suicide Squad","date":"2021-08-04","time":"2021-08-04T15:30:00+01:00","is3d":false,"__v":0},{"_id":"6109a6173501a660f792f8d9","cinema_name":"Wimbledon","showtimeId":"555-5442","film_id":"HO00001379","cinema_id":"555","film_name":"The Suicide Squad","date":"2021-08-04","time":"2021-08-04T15:40:00+01:00","is3d":false,"__v":0},{"_id":"6109a6173501a660f792f8da","cinema_name":"Wimbledon","showtimeId":"555-5440","film_id":"HO00001379","cinema_id":"555","film_name":"The Suicide Squad","date":"2021-08-04","time":"2021-08-04T15:50:00+01:00","is3d":false,"__v":0},{"_id":"6109a6173501a660f792f8db","cinema_name":"Wimbledon","showtimeId":"555-5476","film_id":"HO00001379","cinema_id":"555","film_name":"The Suicide Squad","date":"2021-08-04","time":"2021-08-04T16:09:00+01:00","is3d":false,"__v":0},{"_id":"6109a6173501a660f792f8dc","cinema_name":"Wimbledon","showtimeId":"555-5458","film_id":"HO00001379","cinema_id":"555","film_name":"The Suicide Squad","date":"2021-08-04","time":"2021-08-04T16:40:00+01:00","is3d":false,"__v":0},{"_id":"6109a6173501a660f792f8dd","cinema_name":"Wimbledon","showtimeId":"555-5417","film_id":"HO00001379","cinema_id":"555","film_name":"The Suicide Squad","date":"2021-08-04","time":"2021-08-04T16:50:00+01:00","is3d":false,"__v":0},{"_id":"6109a6173501a660f792f8de","cinema_name":"Wimbledon","showtimeId":"555-5393","film_id":"HO00001379","cinema_id":"555","film_name":"The Suicide Squad","date":"2021-08-04","time":"2021-08-04T17:00:00+01:00","is3d":false,"__v":0},{"_id":"6109a6173501a660f792f8df","cinema_name":"Wimbledon","showtimeId":"555-5456","film_id":"HO00001379","cinema_id":"555","film_name":"The Suicide Squad","date":"2021-08-04","time":"2021-08-04T17:10:00+01:00","is3d":false,"__v":0},{"_id":"6109a6173501a660f792f8e0","cinema_name":"Wimbledon","showtimeId":"555-5400","film_id":"HO00001379","cinema_id":"555","film_name":"The Suicide Squad","date":"2021-08-04","time":"2021-08-04T17:20:00+01:00","is3d":false,"__v":0},{"_id":"6109a6173501a660f792f8e1","cinema_name":"Wimbledon","showtimeId":"555-5454","film_id":"HO00001379","cinema_id":"555","film_name":"The Suicide Squad","date":"2021-08-04","time":"2021-08-04T17:40:00+01:00","is3d":false,"__v":0},{"_id":"6109a6173501a660f792f8e2","cinema_name":"Wimbledon","showtimeId":"555-5424","film_id":"HO00001379","cinema_id":"555","film_name":"The Suicide Squad","date":"2021-08-04","time":"2021-08-04T17:50:00+01:00","is3d":false,"__v":0},{"_id":"6109a6173501a660f792f8e3","cinema_name":"Wimbledon","showtimeId":"555-3903","film_id":"HO00001379","cinema_id":"555","film_name":"The Suicide Squad","date":"2021-08-04","time":"2021-08-04T17:50:00+01:00","is3d":false,"__v":0},{"_id":"6109a6173501a660f792f8e4","cinema_name":"Wimbledon","showtimeId":"555-5428","film_id":"HO00001379","cinema_id":"555","film_name":"The Suicide Squad","date":"2021-08-04","time":"2021-08-04T18:00:00+01:00","is3d":false,"__v":0},{"_id":"6109a6173501a660f792f8e5","cinema_name":"Wimbledon","showtimeId":"555-5386","film_id":"HO00001379","cinema_id":"555","film_name":"The Suicide Squad","date":"2021-08-04","time":"2021-08-04T18:20:00+01:00","is3d":false,"__v":0},{"_id":"6109a6173501a660f792f8e6","cinema_name":"Wimbledon","showtimeId":"555-5452","film_id":"HO00001379","cinema_id":"555","film_name":"The Suicide Squad","date":"2021-08-04","time":"2021-08-04T19:00:00+01:00","is3d":false,"__v":0},{"_id":"6109a6173501a660f792f8e7","cinema_name":"Wimbledon","showtimeId":"555-5465","film_id":"HO00001379","cinema_id":"555","film_name":"The Suicide Squad","date":"2021-08-04","time":"2021-08-04T19:10:00+01:00","is3d":false,"__v":0},{"_id":"6109a6173501a660f792f8e8","cinema_name":"Wimbledon","showtimeId":"555-5389","film_id":"HO00001379","cinema_id":"555","film_name":"The Suicide Squad","date":"2021-08-04","time":"2021-08-04T19:30:00+01:00","is3d":false,"__v":0},{"_id":"6109a6173501a660f792f8e9","cinema_name":"Wimbledon","showtimeId":"555-5413","film_id":"HO00001379","cinema_id":"555","film_name":"The Suicide Squad","date":"2021-08-04","time":"2021-08-04T19:40:00+01:00","is3d":false,"__v":0},{"_id":"6109a6173501a660f792f8ea","cinema_name":"Wimbledon","showtimeId":"555-5450","film_id":"HO00001379","cinema_id":"555","film_name":"The Suicide Squad","date":"2021-08-04","time":"2021-08-04T20:00:00+01:00","is3d":false,"__v":0},{"_id":"6109a6173501a660f792f8eb","cinema_name":"Wimbledon","showtimeId":"555-5463","film_id":"HO00001379","cinema_id":"555","film_name":"The Suicide Squad","date":"2021-08-04","time":"2021-08-04T20:10:00+01:00","is3d":false,"__v":0},{"_id":"6109a6173501a660f792f8ec","cinema_name":"Wimbledon","showtimeId":"555-3904","film_id":"HO00001379","cinema_id":"555","film_name":"The Suicide Squad","date":"2021-08-04","time":"2021-08-04T20:20:00+01:00","is3d":false,"__v":0},{"_id":"6109a6173501a660f792f8ed","cinema_name":"Wimbledon","showtimeId":"555-5388","film_id":"HO00001379","cinema_id":"555","film_name":"The Suicide Squad","date":"2021-08-04","time":"2021-08-04T20:30:00+01:00","is3d":false,"__v":0},{"_id":"6109a6173501a660f792f8ee","cinema_name":"Wimbledon","showtimeId":"555-5399","film_id":"HO00001379","cinema_id":"555","film_name":"The Suicide Squad","date":"2021-08-04","time":"2021-08-04T20:40:00+01:00","is3d":false,"__v":0},{"_id":"6109a6173501a660f792f8ef","cinema_name":"Wimbledon","showtimeId":"555-5469","film_id":"HO00001379","cinema_id":"555","film_name":"The Suicide Squad","date":"2021-08-04","time":"2021-08-04T20:50:00+01:00","is3d":false,"__v":0},{"_id":"6109a6173501a660f792f8f0","cinema_name":"Wimbledon","showtimeId":"555-5461","film_id":"HO00001379","cinema_id":"555","film_name":"The Suicide Squad","date":"2021-08-04","time":"2021-08-04T21:00:00+01:00","is3d":false,"__v":0},{"_id":"6109a6173501a660f792f8f1","cinema_name":"Wimbledon","showtimeId":"555-5385","film_id":"HO00001379","cinema_id":"555","film_name":"The Suicide Squad","date":"2021-08-04","time":"2021-08-04T21:20:00+01:00","is3d":false,"__v":0},{"_id":"6109a61a3501a660f793a27d","cinema_name":"Wimbledon","showtimeId":"555-5404","film_id":"HO00001379","cinema_id":"555","film_name":"The Suicide Squad","date":"2021-08-05","time":"2021-08-05T10:00:00+01:00","is3d":false,"__v":0},{"_id":"6109a61a3501a660f793a27e","cinema_name":"Wimbledon","showtimeId":"555-5470","film_id":"HO00001379","cinema_id":"555","film_name":"The Suicide Squad","date":"2021-08-05","time":"2021-08-05T10:10:00+01:00","is3d":false,"__v":0},{"_id":"6109a61a3501a660f793a27f","cinema_name":"Wimbledon","showtimeId":"555-5484","film_id":"HO00001379","cinema_id":"555","film_name":"The Suicide Squad","date":"2021-08-05","time":"2021-08-05T10:20:00+01:00","is3d":false,"__v":0},{"_id":"6109a61a3501a660f793a280","cinema_name":"Wimbledon","showtimeId":"555-5432","film_id":"HO00001379","cinema_id":"555","film_name":"The Suicide Squad","date":"2021-08-05","time":"2021-08-05T10:30:00+01:00","is3d":false,"__v":0},{"_id":"6109a61a3501a660f793a281","cinema_name":"Wimbledon","showtimeId":"555-5438","film_id":"HO00001379","cinema_id":"555","film_name":"The Suicide Squad","date":"2021-08-05","time":"2021-08-05T10:50:00+01:00","is3d":false,"__v":0},{"_id":"6109a61a3501a660f793a282","cinema_name":"Wimbledon","showtimeId":"555-5416","film_id":"HO00001379","cinema_id":"555","film_name":"The Suicide Squad","date":"2021-08-05","time":"2021-08-05T10:50:00+01:00","is3d":false,"__v":0},{"_id":"6109a61a3501a660f793a283","cinema_name":"Wimbledon","showtimeId":"555-5488","film_id":"HO00001379","cinema_id":"555","film_name":"The Suicide Squad","date":"2021-08-05","time":"2021-08-05T11:00:00+01:00","is3d":false,"__v":0},{"_id":"6109a61a3501a660f793a284","cinema_name":"Wimbledon","showtimeId":"555-5434","film_id":"HO00001379","cinema_id":"555","film_name":"The Suicide Squad","date":"2021-08-05","time":"2021-08-05T11:10:00+01:00","is3d":false,"__v":0},{"_id":"6109a61a3501a660f793a285","cinema_name":"Wimbledon","showtimeId":"555-5406","film_id":"HO00001379","cinema_id":"555","film_name":"The Suicide Squad","date":"2021-08-05","time":"2021-08-05T11:30:00+01:00","is3d":false,"__v":0},{"_id":"6109a61a3501a660f793a286","cinema_name":"Wimbledon","showtimeId":"555-5392","film_id":"HO00001379","cinema_id":"555","film_name":"The Suicide Squad","date":"2021-08-05","time":"2021-08-05T12:00:00+01:00","is3d":false,"__v":0},{"_id":"6109a61a3501a660f793a287","cinema_name":"Wimbledon","showtimeId":"555-5429","film_id":"HO00001379","cinema_id":"555","film_name":"The Suicide Squad","date":"2021-08-05","time":"2021-08-05T12:00:00+01:00","is3d":false,"__v":0},{"_id":"6109a61a3501a660f793a288","cinema_name":"Wimbledon","showtimeId":"555-5403","film_id":"HO00001379","cinema_id":"555","film_name":"The Suicide Squad","date":"2021-08-05","time":"2021-08-05T12:10:00+01:00","is3d":false,"__v":0},{"_id":"6109a61a3501a660f793a289","cinema_name":"Wimbledon","showtimeId":"555-5449","film_id":"HO00001379","cinema_id":"555","film_name":"The Suicide Squad","date":"2021-08-05","time":"2021-08-05T12:20:00+01:00","is3d":false,"__v":0},{"_id":"6109a61a3501a660f793a28a","cinema_name":"Wimbledon","showtimeId":"555-5419","film_id":"HO00001379","cinema_id":"555","film_name":"The Suicide Squad","date":"2021-08-05","time":"2021-08-05T13:00:00+01:00","is3d":false,"__v":0},{"_id":"6109a61a3501a660f793a28b","cinema_name":"Wimbledon","showtimeId":"555-5471","film_id":"HO00001379","cinema_id":"555","film_name":"The Suicide Squad","date":"2021-08-05","time":"2021-08-05T13:10:00+01:00","is3d":false,"__v":0},{"_id":"6109a61a3501a660f793a28c","cinema_name":"Wimbledon","showtimeId":"555-5447","film_id":"HO00001379","cinema_id":"555","film_name":"The Suicide Squad","date":"2021-08-05","time":"2021-08-05T13:20:00+01:00","is3d":false,"__v":0},{"_id":"6109a61a3501a660f793a28d","cinema_name":"Wimbledon","showtimeId":"555-5466","film_id":"HO00001379","cinema_id":"555","film_name":"The Suicide Squad","date":"2021-08-05","time":"2021-08-05T13:30:00+01:00","is3d":false,"__v":0},{"_id":"6109a61a3501a660f793a28e","cinema_name":"Wimbledon","showtimeId":"555-5415","film_id":"HO00001379","cinema_id":"555","film_name":"The Suicide Squad","date":"2021-08-05","time":"2021-08-05T13:50:00+01:00","is3d":false,"__v":0},{"_id":"6109a61a3501a660f793a28f","cinema_name":"Wimbledon","showtimeId":"555-5396","film_id":"HO00001379","cinema_id":"555","film_name":"The Suicide Squad","date":"2021-08-05","time":"2021-08-05T14:00:00+01:00","is3d":false,"__v":0},{"_id":"6109a61a3501a660f793a290","cinema_name":"Wimbledon","showtimeId":"555-5445","film_id":"HO00001379","cinema_id":"555","film_name":"The Suicide Squad","date":"2021-08-05","time":"2021-08-05T14:10:00+01:00","is3d":false,"__v":0},{"_id":"6109a61a3501a660f793a291","cinema_name":"Wimbledon","showtimeId":"555-5443","film_id":"HO00001379","cinema_id":"555","film_name":"The Suicide Squad","date":"2021-08-05","time":"2021-08-05T14:20:00+01:00","is3d":false,"__v":0},{"_id":"6109a61a3501a660f793a292","cinema_name":"Wimbledon","showtimeId":"555-5391","film_id":"HO00001379","cinema_id":"555","film_name":"The Suicide Squad","date":"2021-08-05","time":"2021-08-05T14:30:00+01:00","is3d":false,"__v":0},{"_id":"6109a61a3501a660f793a293","cinema_name":"Wimbledon","showtimeId":"555-5430","film_id":"HO00001379","cinema_id":"555","film_name":"The Suicide Squad","date":"2021-08-05","time":"2021-08-05T14:50:00+01:00","is3d":false,"__v":0},{"_id":"6109a61a3501a660f793a294","cinema_name":"Wimbledon","showtimeId":"555-5411","film_id":"HO00001379","cinema_id":"555","film_name":"The Suicide Squad","date":"2021-08-05","time":"2021-08-05T15:10:00+01:00","is3d":false,"__v":0},{"_id":"6109a61a3501a660f793a295","cinema_name":"Wimbledon","showtimeId":"555-5420","film_id":"HO00001379","cinema_id":"555","film_name":"The Suicide Squad","date":"2021-08-05","time":"2021-08-05T15:30:00+01:00","is3d":false,"__v":0},{"_id":"6109a61a3501a660f793a296","cinema_name":"Wimbledon","showtimeId":"555-5441","film_id":"HO00001379","cinema_id":"555","film_name":"The Suicide Squad","date":"2021-08-05","time":"2021-08-05T15:40:00+01:00","is3d":false,"__v":0},{"_id":"6109a61a3501a660f793a297","cinema_name":"Wimbledon","showtimeId":"555-5459","film_id":"HO00001379","cinema_id":"555","film_name":"The Suicide Squad","date":"2021-08-05","time":"2021-08-05T15:50:00+01:00","is3d":false,"__v":0},{"_id":"6109a61a3501a660f793a298","cinema_name":"Wimbledon","showtimeId":"555-5472","film_id":"HO00001379","cinema_id":"555","film_name":"The Suicide Squad","date":"2021-08-05","time":"2021-08-05T16:09:00+01:00","is3d":false,"__v":0},{"_id":"6109a61a3501a660f793a299","cinema_name":"Wimbledon","showtimeId":"555-5457","film_id":"HO00001379","cinema_id":"555","film_name":"The Suicide Squad","date":"2021-08-05","time":"2021-08-05T16:40:00+01:00","is3d":false,"__v":0},{"_id":"6109a61a3501a660f793a29a","cinema_name":"Wimbledon","showtimeId":"555-5414","film_id":"HO00001379","cinema_id":"555","film_name":"The Suicide Squad","date":"2021-08-05","time":"2021-08-05T16:50:00+01:00","is3d":false,"__v":0},{"_id":"6109a61a3501a660f793a29b","cinema_name":"Wimbledon","showtimeId":"555-5390","film_id":"HO00001379","cinema_id":"555","film_name":"The Suicide Squad","date":"2021-08-05","time":"2021-08-05T17:00:00+01:00","is3d":false,"__v":0},{"_id":"6109a61a3501a660f793a29c","cinema_name":"Wimbledon","showtimeId":"555-5455","film_id":"HO00001379","cinema_id":"555","film_name":"The Suicide Squad","date":"2021-08-05","time":"2021-08-05T17:10:00+01:00","is3d":false,"__v":0},{"_id":"6109a61a3501a660f793a29d","cinema_name":"Wimbledon","showtimeId":"555-5397","film_id":"HO00001379","cinema_id":"555","film_name":"The Suicide Squad","date":"2021-08-05","time":"2021-08-05T17:20:00+01:00","is3d":false,"__v":0},{"_id":"6109a61a3501a660f793a29e","cinema_name":"Wimbledon","showtimeId":"555-5453","film_id":"HO00001379","cinema_id":"555","film_name":"The Suicide Squad","date":"2021-08-05","time":"2021-08-05T17:40:00+01:00","is3d":false,"__v":0},{"_id":"6109a61a3501a660f793a29f","cinema_name":"Wimbledon","showtimeId":"555-5431","film_id":"HO00001379","cinema_id":"555","film_name":"The Suicide Squad","date":"2021-08-05","time":"2021-08-05T17:50:00+01:00","is3d":false,"__v":0},{"_id":"6109a61a3501a660f793a2a0","cinema_name":"Wimbledon","showtimeId":"555-5421","film_id":"HO00001379","cinema_id":"555","film_name":"The Suicide Squad","date":"2021-08-05","time":"2021-08-05T18:00:00+01:00","is3d":false,"__v":0},{"_id":"6109a61a3501a660f793a2a1","cinema_name":"Wimbledon","showtimeId":"555-5384","film_id":"HO00001379","cinema_id":"555","film_name":"The Suicide Squad","date":"2021-08-05","time":"2021-08-05T18:10:00+01:00","is3d":false,"__v":0},{"_id":"6109a61a3501a660f793a2a2","cinema_name":"Wimbledon","showtimeId":"555-5410","film_id":"HO00001379","cinema_id":"555","film_name":"The Suicide Squad","date":"2021-08-05","time":"2021-08-05T18:30:00+01:00","is3d":false,"__v":0},{"_id":"6109a61a3501a660f793a2a3","cinema_name":"Wimbledon","showtimeId":"555-5451","film_id":"HO00001379","cinema_id":"555","film_name":"The Suicide Squad","date":"2021-08-05","time":"2021-08-05T19:00:00+01:00","is3d":false,"__v":0},{"_id":"6109a61a3501a660f793a2a4","cinema_name":"Wimbledon","showtimeId":"555-5473","film_id":"HO00001379","cinema_id":"555","film_name":"The Suicide Squad","date":"2021-08-05","time":"2021-08-05T19:10:00+01:00","is3d":false,"__v":0},{"_id":"6109a61a3501a660f793a2a5","cinema_name":"Wimbledon","showtimeId":"555-5402","film_id":"HO00001379","cinema_id":"555","film_name":"The Suicide Squad","date":"2021-08-05","time":"2021-08-05T19:30:00+01:00","is3d":false,"__v":0},{"_id":"6109a61a3501a660f793a2a6","cinema_name":"Wimbledon","showtimeId":"555-5412","film_id":"HO00001379","cinema_id":"555","film_name":"The Suicide Squad","date":"2021-08-05","time":"2021-08-05T19:40:00+01:00","is3d":false,"__v":0},{"_id":"6109a61a3501a660f793a2a7","cinema_name":"Wimbledon","showtimeId":"555-5464","film_id":"HO00001379","cinema_id":"555","film_name":"The Suicide Squad","date":"2021-08-05","time":"2021-08-05T20:00:00+01:00","is3d":false,"__v":0},{"_id":"6109a61a3501a660f793a2a8","cinema_name":"Wimbledon","showtimeId":"555-5462","film_id":"HO00001379","cinema_id":"555","film_name":"The Suicide Squad","date":"2021-08-05","time":"2021-08-05T20:10:00+01:00","is3d":false,"__v":0},{"_id":"6109a61a3501a660f793a2a9","cinema_name":"Wimbledon","showtimeId":"555-5387","film_id":"HO00001379","cinema_id":"555","film_name":"The Suicide Squad","date":"2021-08-05","time":"2021-08-05T20:30:00+01:00","is3d":false,"__v":0},{"_id":"6109a61a3501a660f793a2aa","cinema_name":"Wimbledon","showtimeId":"555-5398","film_id":"HO00001379","cinema_id":"555","film_name":"The Suicide Squad","date":"2021-08-05","time":"2021-08-05T20:40:00+01:00","is3d":false,"__v":0},{"_id":"6109a61a3501a660f793a2ab","cinema_name":"Wimbledon","showtimeId":"555-5468","film_id":"HO00001379","cinema_id":"555","film_name":"The Suicide Squad","date":"2021-08-05","time":"2021-08-05T20:50:00+01:00","is3d":false,"__v":0},{"_id":"6109a61a3501a660f793a2ac","cinema_name":"Wimbledon","showtimeId":"555-5460","film_id":"HO00001379","cinema_id":"555","film_name":"The Suicide Squad","date":"2021-08-05","time":"2021-08-05T21:00:00+01:00","is3d":false,"__v":0},{"_id":"6109a61a3501a660f793a2ad","cinema_name":"Wimbledon","showtimeId":"555-5409","film_id":"HO00001379","cinema_id":"555","film_name":"The Suicide Squad","date":"2021-08-05","time":"2021-08-05T21:20:00+01:00","is3d":false,"__v":0},{"_id":"6109a61a3501a660f793a2ae","cinema_name":"Wimbledon","showtimeId":"555-5383","film_id":"HO00001379","cinema_id":"555","film_name":"The Suicide Squad","date":"2021-08-05","time":"2021-08-05T21:30:00+01:00","is3d":false,"__v":0},{"_id":"6109a61e3501a660f7944dd3","cinema_name":"Wimbledon","showtimeId":"555-5581","film_id":"HO00001379","cinema_id":"555","film_name":"The Suicide Squad","date":"2021-08-06","time":"2021-08-06T10:00:00+01:00","is3d":false,"__v":0},{"_id":"6109a61e3501a660f7944dd4","cinema_name":"Wimbledon","showtimeId":"555-5578","film_id":"HO00001379","cinema_id":"555","film_name":"The Suicide Squad","date":"2021-08-06","time":"2021-08-06T10:10:00+01:00","is3d":false,"__v":0},{"_id":"6109a61e3501a660f7944dd5","cinema_name":"Wimbledon","showtimeId":"555-5582","film_id":"HO00001379","cinema_id":"555","film_name":"The Suicide Squad","date":"2021-08-06","time":"2021-08-06T10:20:00+01:00","is3d":false,"__v":0},{"_id":"6109a61e3501a660f7944dd6","cinema_name":"Wimbledon","showtimeId":"555-5568","film_id":"HO00001379","cinema_id":"555","film_name":"The Suicide Squad","date":"2021-08-06","time":"2021-08-06T10:20:00+01:00","is3d":false,"__v":0},{"_id":"6109a61e3501a660f7944dd7","cinema_name":"Wimbledon","showtimeId":"555-5603","film_id":"HO00001379","cinema_id":"555","film_name":"The Suicide Squad","date":"2021-08-06","time":"2021-08-06T10:30:00+01:00","is3d":false,"__v":0},{"_id":"6109a61e3501a660f7944dd8","cinema_name":"Wimbledon","showtimeId":"555-5569","film_id":"HO00001379","cinema_id":"555","film_name":"The Suicide Squad","date":"2021-08-06","time":"2021-08-06T10:40:00+01:00","is3d":false,"__v":0},{"_id":"6109a61e3501a660f7944dd9","cinema_name":"Wimbledon","showtimeId":"555-5596","film_id":"HO00001379","cinema_id":"555","film_name":"The Suicide Squad","date":"2021-08-06","time":"2021-08-06T10:50:00+01:00","is3d":false,"__v":0},{"_id":"6109a61e3501a660f7944dda","cinema_name":"Wimbledon","showtimeId":"555-5499","film_id":"HO00001379","cinema_id":"555","film_name":"The Suicide Squad","date":"2021-08-06","time":"2021-08-06T11:10:00+01:00","is3d":false,"__v":0},{"_id":"6109a61e3501a660f7944ddb","cinema_name":"Wimbledon","showtimeId":"555-5587","film_id":"HO00001379","cinema_id":"555","film_name":"The Suicide Squad","date":"2021-08-06","time":"2021-08-06T11:20:00+01:00","is3d":false,"__v":0},{"_id":"6109a61e3501a660f7944ddc","cinema_name":"Wimbledon","showtimeId":"555-5600","film_id":"HO00001379","cinema_id":"555","film_name":"The Suicide Squad","date":"2021-08-06","time":"2021-08-06T11:50:00+01:00","is3d":false,"__v":0},{"_id":"6109a61e3501a660f7944ddd","cinema_name":"Wimbledon","showtimeId":"555-5503","film_id":"HO00001379","cinema_id":"555","film_name":"The Suicide Squad","date":"2021-08-06","time":"2021-08-06T12:10:00+01:00","is3d":false,"__v":0},{"_id":"6109a61e3501a660f7944dde","cinema_name":"Wimbledon","showtimeId":"555-5576","film_id":"HO00001379","cinema_id":"555","film_name":"The Suicide Squad","date":"2021-08-06","time":"2021-08-06T12:20:00+01:00","is3d":false,"__v":0},{"_id":"6109a61e3501a660f7944ddf","cinema_name":"Wimbledon","showtimeId":"555-5583","film_id":"HO00001379","cinema_id":"555","film_name":"The Suicide Squad","date":"2021-08-06","time":"2021-08-06T12:40:00+01:00","is3d":false,"__v":0},{"_id":"6109a61e3501a660f7944de0","cinema_name":"Wimbledon","showtimeId":"555-5593","film_id":"HO00001379","cinema_id":"555","film_name":"The Suicide Squad","date":"2021-08-06","time":"2021-08-06T12:40:00+01:00","is3d":false,"__v":0},{"_id":"6109a61e3501a660f7944de1","cinema_name":"Wimbledon","showtimeId":"555-5602","film_id":"HO00001379","cinema_id":"555","film_name":"The Suicide Squad","date":"2021-08-06","time":"2021-08-06T13:00:00+01:00","is3d":false,"__v":0},{"_id":"6109a61e3501a660f7944de2","cinema_name":"Wimbledon","showtimeId":"555-5577","film_id":"HO00001379","cinema_id":"555","film_name":"The Suicide Squad","date":"2021-08-06","time":"2021-08-06T13:10:00+01:00","is3d":false,"__v":0},{"_id":"6109a61e3501a660f7944de3","cinema_name":"Wimbledon","showtimeId":"555-5597","film_id":"HO00001379","cinema_id":"555","film_name":"The Suicide Squad","date":"2021-08-06","time":"2021-08-06T13:20:00+01:00","is3d":false,"__v":0},{"_id":"6109a61e3501a660f7944de4","cinema_name":"Wimbledon","showtimeId":"555-5570","film_id":"HO00001379","cinema_id":"555","film_name":"The Suicide Squad","date":"2021-08-06","time":"2021-08-06T13:30:00+01:00","is3d":false,"__v":0},{"_id":"6109a61e3501a660f7944de5","cinema_name":"Wimbledon","showtimeId":"555-5496","film_id":"HO00001379","cinema_id":"555","film_name":"The Suicide Squad","date":"2021-08-06","time":"2021-08-06T13:40:00+01:00","is3d":false,"__v":0},{"_id":"6109a61e3501a660f7944de6","cinema_name":"Wimbledon","showtimeId":"555-5588","film_id":"HO00001379","cinema_id":"555","film_name":"The Suicide Squad","date":"2021-08-06","time":"2021-08-06T13:50:00+01:00","is3d":false,"__v":0},{"_id":"6109a61e3501a660f7944de7","cinema_name":"Wimbledon","showtimeId":"555-5500","film_id":"HO00001379","cinema_id":"555","film_name":"The Suicide Squad","date":"2021-08-06","time":"2021-08-06T14:10:00+01:00","is3d":false,"__v":0},{"_id":"6109a61e3501a660f7944de8","cinema_name":"Wimbledon","showtimeId":"555-5601","film_id":"HO00001379","cinema_id":"555","film_name":"The Suicide Squad","date":"2021-08-06","time":"2021-08-06T14:20:00+01:00","is3d":false,"__v":0},{"_id":"6109a61e3501a660f7944de9","cinema_name":"Wimbledon","showtimeId":"555-5573","film_id":"HO00001379","cinema_id":"555","film_name":"The Suicide Squad","date":"2021-08-06","time":"2021-08-06T14:40:00+01:00","is3d":false,"__v":0},{"_id":"6109a61e3501a660f7944dea","cinema_name":"Wimbledon","showtimeId":"555-5504","film_id":"HO00001379","cinema_id":"555","film_name":"The Suicide Squad","date":"2021-08-06","time":"2021-08-06T14:50:00+01:00","is3d":false,"__v":0},{"_id":"6109a61e3501a660f7944deb","cinema_name":"Wimbledon","showtimeId":"555-5898","film_id":"HO00001379","cinema_id":"555","film_name":"The Suicide Squad","date":"2021-08-06","time":"2021-08-06T15:00:00+01:00","is3d":false,"__v":0},{"_id":"6109a61e3501a660f7944dec","cinema_name":"Wimbledon","showtimeId":"555-5604","film_id":"HO00001379","cinema_id":"555","film_name":"The Suicide Squad","date":"2021-08-06","time":"2021-08-06T15:30:00+01:00","is3d":false,"__v":0},{"_id":"6109a61e3501a660f7944ded","cinema_name":"Wimbledon","showtimeId":"555-5592","film_id":"HO00001379","cinema_id":"555","film_name":"The Suicide Squad","date":"2021-08-06","time":"2021-08-06T15:50:00+01:00","is3d":false,"__v":0},{"_id":"6109a61e3501a660f7944dee","cinema_name":"Wimbledon","showtimeId":"555-5580","film_id":"HO00001379","cinema_id":"555","film_name":"The Suicide Squad","date":"2021-08-06","time":"2021-08-06T16:10:00+01:00","is3d":false,"__v":0},{"_id":"6109a61e3501a660f7944def","cinema_name":"Wimbledon","showtimeId":"555-5589","film_id":"HO00001379","cinema_id":"555","film_name":"The Suicide Squad","date":"2021-08-06","time":"2021-08-06T16:20:00+01:00","is3d":false,"__v":0},{"_id":"6109a61e3501a660f7944df0","cinema_name":"Wimbledon","showtimeId":"555-5598","film_id":"HO00001379","cinema_id":"555","film_name":"The Suicide Squad","date":"2021-08-06","time":"2021-08-06T16:30:00+01:00","is3d":false,"__v":0},{"_id":"6109a61e3501a660f7944df1","cinema_name":"Wimbledon","showtimeId":"555-5571","film_id":"HO00001379","cinema_id":"555","film_name":"The Suicide Squad","date":"2021-08-06","time":"2021-08-06T16:40:00+01:00","is3d":false,"__v":0},{"_id":"6109a61e3501a660f7944df2","cinema_name":"Wimbledon","showtimeId":"555-5497","film_id":"HO00001379","cinema_id":"555","film_name":"The Suicide Squad","date":"2021-08-06","time":"2021-08-06T16:50:00+01:00","is3d":false,"__v":0},{"_id":"6109a61e3501a660f7944df3","cinema_name":"Wimbledon","showtimeId":"555-5501","film_id":"HO00001379","cinema_id":"555","film_name":"The Suicide Squad","date":"2021-08-06","time":"2021-08-06T17:10:00+01:00","is3d":false,"__v":0},{"_id":"6109a61e3501a660f7944df4","cinema_name":"Wimbledon","showtimeId":"555-5507","film_id":"HO00001379","cinema_id":"555","film_name":"The Suicide Squad","date":"2021-08-06","time":"2021-08-06T17:20:00+01:00","is3d":false,"__v":0},{"_id":"6109a61e3501a660f7944df5","cinema_name":"Wimbledon","showtimeId":"555-5505","film_id":"HO00001379","cinema_id":"555","film_name":"The Suicide Squad","date":"2021-08-06","time":"2021-08-06T17:40:00+01:00","is3d":false,"__v":0},{"_id":"6109a61e3501a660f7944df6","cinema_name":"Wimbledon","showtimeId":"555-5574","film_id":"HO00001379","cinema_id":"555","film_name":"The Suicide Squad","date":"2021-08-06","time":"2021-08-06T17:50:00+01:00","is3d":false,"__v":0},{"_id":"6109a61e3501a660f7944df7","cinema_name":"Wimbledon","showtimeId":"555-5605","film_id":"HO00001379","cinema_id":"555","film_name":"The Suicide Squad","date":"2021-08-06","time":"2021-08-06T18:00:00+01:00","is3d":false,"__v":0},{"_id":"6109a61e3501a660f7944df8","cinema_name":"Wimbledon","showtimeId":"555-5585","film_id":"HO00001379","cinema_id":"555","film_name":"The Suicide Squad","date":"2021-08-06","time":"2021-08-06T18:10:00+01:00","is3d":false,"__v":0},{"_id":"6109a61e3501a660f7944df9","cinema_name":"Wimbledon","showtimeId":"555-5594","film_id":"HO00001379","cinema_id":"555","film_name":"The Suicide Squad","date":"2021-08-06","time":"2021-08-06T18:40:00+01:00","is3d":false,"__v":0},{"_id":"6109a61e3501a660f7944dfa","cinema_name":"Wimbledon","showtimeId":"555-5591","film_id":"HO00001379","cinema_id":"555","film_name":"The Suicide Squad","date":"2021-08-06","time":"2021-08-06T18:50:00+01:00","is3d":false,"__v":0},{"_id":"6109a61e3501a660f7944dfb","cinema_name":"Wimbledon","showtimeId":"555-5579","film_id":"HO00001379","cinema_id":"555","film_name":"The Suicide Squad","date":"2021-08-06","time":"2021-08-06T19:10:00+01:00","is3d":false,"__v":0},{"_id":"6109a61e3501a660f7944dfc","cinema_name":"Wimbledon","showtimeId":"555-5572","film_id":"HO00001379","cinema_id":"555","film_name":"The Suicide Squad","date":"2021-08-06","time":"2021-08-06T19:30:00+01:00","is3d":false,"__v":0},{"_id":"6109a61e3501a660f7944dfd","cinema_name":"Wimbledon","showtimeId":"555-5599","film_id":"HO00001379","cinema_id":"555","film_name":"The Suicide Squad","date":"2021-08-06","time":"2021-08-06T19:40:00+01:00","is3d":false,"__v":0},{"_id":"6109a61e3501a660f7944dfe","cinema_name":"Wimbledon","showtimeId":"555-5498","film_id":"HO00001379","cinema_id":"555","film_name":"The Suicide Squad","date":"2021-08-06","time":"2021-08-06T20:00:00+01:00","is3d":false,"__v":0},{"_id":"6109a61e3501a660f7944dff","cinema_name":"Wimbledon","showtimeId":"555-5502","film_id":"HO00001379","cinema_id":"555","film_name":"The Suicide Squad","date":"2021-08-06","time":"2021-08-06T20:10:00+01:00","is3d":false,"__v":0},{"_id":"6109a61e3501a660f7944e00","cinema_name":"Wimbledon","showtimeId":"555-5506","film_id":"HO00001379","cinema_id":"555","film_name":"The Suicide Squad","date":"2021-08-06","time":"2021-08-06T20:20:00+01:00","is3d":false,"__v":0},{"_id":"6109a61e3501a660f7944e01","cinema_name":"Wimbledon","showtimeId":"555-5508","film_id":"HO00001379","cinema_id":"555","film_name":"The Suicide Squad","date":"2021-08-06","time":"2021-08-06T20:40:00+01:00","is3d":false,"__v":0},{"_id":"6109a61e3501a660f7944e02","cinema_name":"Wimbledon","showtimeId":"555-5575","film_id":"HO00001379","cinema_id":"555","film_name":"The Suicide Squad","date":"2021-08-06","time":"2021-08-06T21:00:00+01:00","is3d":false,"__v":0},{"_id":"6109a61e3501a660f7944e03","cinema_name":"Wimbledon","showtimeId":"555-5606","film_id":"HO00001379","cinema_id":"555","film_name":"The Suicide Squad","date":"2021-08-06","time":"2021-08-06T21:10:00+01:00","is3d":false,"__v":0},{"_id":"6109a61e3501a660f7944e04","cinema_name":"Wimbledon","showtimeId":"555-5586","film_id":"HO00001379","cinema_id":"555","film_name":"The Suicide Squad","date":"2021-08-06","time":"2021-08-06T21:20:00+01:00","is3d":false,"__v":0},{"_id":"6109a61e3501a660f7944e05","cinema_name":"Wimbledon","showtimeId":"555-5595","film_id":"HO00001379","cinema_id":"555","film_name":"The Suicide Squad","date":"2021-08-06","time":"2021-08-06T21:30:00+01:00","is3d":false,"__v":0},{"_id":"6109a61e3501a660f7944e06","cinema_name":"Wimbledon","showtimeId":"555-5590","film_id":"HO00001379","cinema_id":"555","film_name":"The Suicide Squad","date":"2021-08-06","time":"2021-08-06T22:00:00+01:00","is3d":false,"__v":0},{"_id":"6109a61e3501a660f7944e07","cinema_name":"Wimbledon","showtimeId":"555-5871","film_id":"HO00001379","cinema_id":"555","film_name":"The Suicide Squad","date":"2021-08-06","time":"2021-08-06T22:15:00+01:00","is3d":false,"__v":0},{"_id":"6109a61e3501a660f7944e08","cinema_name":"Wimbledon","showtimeId":"555-5872","film_id":"HO00001379","cinema_id":"555","film_name":"The Suicide Squad","date":"2021-08-06","time":"2021-08-06T22:30:00+01:00","is3d":false,"__v":0},{"_id":"6109a61e3501a660f7944e09","cinema_name":"Wimbledon","showtimeId":"555-5873","film_id":"HO00001379","cinema_id":"555","film_name":"The Suicide Squad","date":"2021-08-06","time":"2021-08-06T22:50:00+01:00","is3d":false,"__v":0}]}