{"_id":{"film_id":"HO00001364","cinema_id":"843"},"file":[{"_id":"6109a6173501a660f79315b8","cinema_name":"Rochdale","showtimeId":"843-4555","film_id":"HO00001364","cinema_id":"843","film_name":"Fast & Furious 9","date":"2021-08-04","time":"2021-08-04T10:00:00+01:00","is3d":false,"__v":0},{"_id":"6109a6173501a660f79315b9","cinema_name":"Rochdale","showtimeId":"843-4511","film_id":"HO00001364","cinema_id":"843","film_name":"Fast & Furious 9","date":"2021-08-04","time":"2021-08-04T10:10:00+01:00","is3d":false,"__v":0},{"_id":"6109a6173501a660f79315ba","cinema_name":"Rochdale","showtimeId":"843-4478","film_id":"HO00001364","cinema_id":"843","film_name":"Fast & Furious 9","date":"2021-08-04","time":"2021-08-04T10:30:00+01:00","is3d":false,"__v":0},{"_id":"6109a6173501a660f79315bb","cinema_name":"Rochdale","showtimeId":"843-4482","film_id":"HO00001364","cinema_id":"843","film_name":"Fast & Furious 9","date":"2021-08-04","time":"2021-08-04T10:40:00+01:00","is3d":false,"__v":0},{"_id":"6109a6173501a660f79315bc","cinema_name":"Rochdale","showtimeId":"843-4503","film_id":"HO00001364","cinema_id":"843","film_name":"Fast & Furious 9","date":"2021-08-04","time":"2021-08-04T10:50:00+01:00","is3d":false,"__v":0},{"_id":"6109a6173501a660f79315bd","cinema_name":"Rochdale","showtimeId":"843-4491","film_id":"HO00001364","cinema_id":"843","film_name":"Fast & Furious 9","date":"2021-08-04","time":"2021-08-04T11:10:00+01:00","is3d":false,"__v":0},{"_id":"6109a6173501a660f79315be","cinema_name":"Rochdale","showtimeId":"843-4477","film_id":"HO00001364","cinema_id":"843","film_name":"Fast & Furious 9","date":"2021-08-04","time":"2021-08-04T11:20:00+01:00","is3d":false,"__v":0},{"_id":"6109a6173501a660f79315bf","cinema_name":"Rochdale","showtimeId":"843-4481","film_id":"HO00001364","cinema_id":"843","film_name":"Fast & Furious 9","date":"2021-08-04","time":"2021-08-04T11:30:00+01:00","is3d":false,"__v":0},{"_id":"6109a6173501a660f79315c0","cinema_name":"Rochdale","showtimeId":"843-4495","film_id":"HO00001364","cinema_id":"843","film_name":"Fast & Furious 9","date":"2021-08-04","time":"2021-08-04T12:00:00+01:00","is3d":false,"__v":0},{"_id":"6109a6173501a660f79315c1","cinema_name":"Rochdale","showtimeId":"843-4500","film_id":"HO00001364","cinema_id":"843","film_name":"Fast & Furious 9","date":"2021-08-04","time":"2021-08-04T12:50:00+01:00","is3d":false,"__v":0},{"_id":"6109a6173501a660f79315c2","cinema_name":"Rochdale","showtimeId":"843-4479","film_id":"HO00001364","cinema_id":"843","film_name":"Fast & Furious 9","date":"2021-08-04","time":"2021-08-04T13:00:00+01:00","is3d":false,"__v":0},{"_id":"6109a6173501a660f79315c3","cinema_name":"Rochdale","showtimeId":"843-4498","film_id":"HO00001364","cinema_id":"843","film_name":"Fast & Furious 9","date":"2021-08-04","time":"2021-08-04T13:10:00+01:00","is3d":false,"__v":0},{"_id":"6109a6173501a660f79315c4","cinema_name":"Rochdale","showtimeId":"843-4504","film_id":"HO00001364","cinema_id":"843","film_name":"Fast & Furious 9","date":"2021-08-04","time":"2021-08-04T13:20:00+01:00","is3d":false,"__v":0},{"_id":"6109a6173501a660f79315c5","cinema_name":"Rochdale","showtimeId":"843-4490","film_id":"HO00001364","cinema_id":"843","film_name":"Fast & Furious 9","date":"2021-08-04","time":"2021-08-04T13:40:00+01:00","is3d":false,"__v":0},{"_id":"6109a6173501a660f79315c6","cinema_name":"Rochdale","showtimeId":"843-4486","film_id":"HO00001364","cinema_id":"843","film_name":"Fast & Furious 9","date":"2021-08-04","time":"2021-08-04T14:00:00+01:00","is3d":false,"__v":0},{"_id":"6109a6173501a660f79315c7","cinema_name":"Rochdale","showtimeId":"843-4492","film_id":"HO00001364","cinema_id":"843","film_name":"Fast & Furious 9","date":"2021-08-04","time":"2021-08-04T14:10:00+01:00","is3d":false,"__v":0},{"_id":"6109a6173501a660f79315c8","cinema_name":"Rochdale","showtimeId":"843-4483","film_id":"HO00001364","cinema_id":"843","film_name":"Fast & Furious 9","date":"2021-08-04","time":"2021-08-04T14:30:00+01:00","is3d":false,"__v":0},{"_id":"6109a6173501a660f79315c9","cinema_name":"Rochdale","showtimeId":"843-4496","film_id":"HO00001364","cinema_id":"843","film_name":"Fast & Furious 9","date":"2021-08-04","time":"2021-08-04T14:50:00+01:00","is3d":false,"__v":0},{"_id":"6109a6173501a660f79315ca","cinema_name":"Rochdale","showtimeId":"843-4480","film_id":"HO00001364","cinema_id":"843","film_name":"Fast & Furious 9","date":"2021-08-04","time":"2021-08-04T15:30:00+01:00","is3d":false,"__v":0},{"_id":"6109a6173501a660f79315cb","cinema_name":"Rochdale","showtimeId":"843-4505","film_id":"HO00001364","cinema_id":"843","film_name":"Fast & Furious 9","date":"2021-08-04","time":"2021-08-04T15:50:00+01:00","is3d":false,"__v":0},{"_id":"6109a6173501a660f79315cc","cinema_name":"Rochdale","showtimeId":"843-4501","film_id":"HO00001364","cinema_id":"843","film_name":"Fast & Furious 9","date":"2021-08-04","time":"2021-08-04T15:50:00+01:00","is3d":false,"__v":0},{"_id":"6109a6173501a660f79315cd","cinema_name":"Rochdale","showtimeId":"843-4499","film_id":"HO00001364","cinema_id":"843","film_name":"Fast & Furious 9","date":"2021-08-04","time":"2021-08-04T16:10:00+01:00","is3d":false,"__v":0},{"_id":"6109a6173501a660f79315ce","cinema_name":"Rochdale","showtimeId":"843-4507","film_id":"HO00001364","cinema_id":"843","film_name":"Fast & Furious 9","date":"2021-08-04","time":"2021-08-04T16:50:00+01:00","is3d":false,"__v":0},{"_id":"6109a6173501a660f79315cf","cinema_name":"Rochdale","showtimeId":"843-4493","film_id":"HO00001364","cinema_id":"843","film_name":"Fast & Furious 9","date":"2021-08-04","time":"2021-08-04T17:10:00+01:00","is3d":false,"__v":0},{"_id":"6109a6173501a660f79315d0","cinema_name":"Rochdale","showtimeId":"843-4485","film_id":"HO00001364","cinema_id":"843","film_name":"Fast & Furious 9","date":"2021-08-04","time":"2021-08-04T17:20:00+01:00","is3d":false,"__v":0},{"_id":"6109a6173501a660f79315d1","cinema_name":"Rochdale","showtimeId":"843-4497","film_id":"HO00001364","cinema_id":"843","film_name":"Fast & Furious 9","date":"2021-08-04","time":"2021-08-04T17:40:00+01:00","is3d":false,"__v":0},{"_id":"6109a6173501a660f79315d2","cinema_name":"Rochdale","showtimeId":"843-4488","film_id":"HO00001364","cinema_id":"843","film_name":"Fast & Furious 9","date":"2021-08-04","time":"2021-08-04T17:50:00+01:00","is3d":false,"__v":0},{"_id":"6109a6173501a660f79315d3","cinema_name":"Rochdale","showtimeId":"843-4509","film_id":"HO00001364","cinema_id":"843","film_name":"Fast & Furious 9","date":"2021-08-04","time":"2021-08-04T18:00:00+01:00","is3d":false,"__v":0},{"_id":"6109a6173501a660f79315d4","cinema_name":"Rochdale","showtimeId":"843-3403","film_id":"HO00001364","cinema_id":"843","film_name":"Fast & Furious 9","date":"2021-08-04","time":"2021-08-04T18:30:00+01:00","is3d":false,"__v":0},{"_id":"6109a6173501a660f79315d5","cinema_name":"Rochdale","showtimeId":"843-4502","film_id":"HO00001364","cinema_id":"843","film_name":"Fast & Furious 9","date":"2021-08-04","time":"2021-08-04T19:00:00+01:00","is3d":false,"__v":0},{"_id":"6109a6173501a660f79315d6","cinema_name":"Rochdale","showtimeId":"843-4508","film_id":"HO00001364","cinema_id":"843","film_name":"Fast & Furious 9","date":"2021-08-04","time":"2021-08-04T19:10:00+01:00","is3d":false,"__v":0},{"_id":"6109a6173501a660f79315d7","cinema_name":"Rochdale","showtimeId":"843-4489","film_id":"HO00001364","cinema_id":"843","film_name":"Fast & Furious 9","date":"2021-08-04","time":"2021-08-04T20:00:00+01:00","is3d":false,"__v":0},{"_id":"6109a6173501a660f79315d8","cinema_name":"Rochdale","showtimeId":"843-4494","film_id":"HO00001364","cinema_id":"843","film_name":"Fast & Furious 9","date":"2021-08-04","time":"2021-08-04T20:10:00+01:00","is3d":false,"__v":0},{"_id":"6109a6173501a660f79315d9","cinema_name":"Rochdale","showtimeId":"843-4476","film_id":"HO00001364","cinema_id":"843","film_name":"Fast & Furious 9","date":"2021-08-04","time":"2021-08-04T20:30:00+01:00","is3d":false,"__v":0},{"_id":"6109a6173501a660f79315da","cinema_name":"Rochdale","showtimeId":"843-4484","film_id":"HO00001364","cinema_id":"843","film_name":"Fast & Furious 9","date":"2021-08-04","time":"2021-08-04T20:40:00+01:00","is3d":false,"__v":0},{"_id":"6109a6173501a660f79315db","cinema_name":"Rochdale","showtimeId":"843-4510","film_id":"HO00001364","cinema_id":"843","film_name":"Fast & Furious 9","date":"2021-08-04","time":"2021-08-04T20:50:00+01:00","is3d":false,"__v":0},{"_id":"6109a6173501a660f79315dc","cinema_name":"Rochdale","showtimeId":"843-4506","film_id":"HO00001364","cinema_id":"843","film_name":"Fast & Furious 9","date":"2021-08-04","time":"2021-08-04T21:00:00+01:00","is3d":false,"__v":0},{"_id":"6109a6173501a660f79315dd","cinema_name":"Rochdale","showtimeId":"843-4487","film_id":"HO00001364","cinema_id":"843","film_name":"Fast & Furious 9","date":"2021-08-04","time":"2021-08-04T21:20:00+01:00","is3d":false,"__v":0},{"_id":"6109a61b3501a660f793be89","cinema_name":"Rochdale","showtimeId":"843-4556","film_id":"HO00001364","cinema_id":"843","film_name":"Fast & Furious 9","date":"2021-08-05","time":"2021-08-05T10:00:00+01:00","is3d":false,"__v":0},{"_id":"6109a61b3501a660f793be8a","cinema_name":"Rochdale","showtimeId":"843-4553","film_id":"HO00001364","cinema_id":"843","film_name":"Fast & Furious 9","date":"2021-08-05","time":"2021-08-05T10:10:00+01:00","is3d":false,"__v":0},{"_id":"6109a61b3501a660f793be8b","cinema_name":"Rochdale","showtimeId":"843-4526","film_id":"HO00001364","cinema_id":"843","film_name":"Fast & Furious 9","date":"2021-08-05","time":"2021-08-05T10:30:00+01:00","is3d":false,"__v":0},{"_id":"6109a61b3501a660f793be8c","cinema_name":"Rochdale","showtimeId":"843-4531","film_id":"HO00001364","cinema_id":"843","film_name":"Fast & Furious 9","date":"2021-08-05","time":"2021-08-05T10:40:00+01:00","is3d":false,"__v":0},{"_id":"6109a61b3501a660f793be8d","cinema_name":"Rochdale","showtimeId":"843-4544","film_id":"HO00001364","cinema_id":"843","film_name":"Fast & Furious 9","date":"2021-08-05","time":"2021-08-05T10:50:00+01:00","is3d":false,"__v":0},{"_id":"6109a61b3501a660f793be8e","cinema_name":"Rochdale","showtimeId":"843-4542","film_id":"HO00001364","cinema_id":"843","film_name":"Fast & Furious 9","date":"2021-08-05","time":"2021-08-05T11:10:00+01:00","is3d":false,"__v":0},{"_id":"6109a61b3501a660f793be8f","cinema_name":"Rochdale","showtimeId":"843-4522","film_id":"HO00001364","cinema_id":"843","film_name":"Fast & Furious 9","date":"2021-08-05","time":"2021-08-05T11:20:00+01:00","is3d":false,"__v":0},{"_id":"6109a61b3501a660f793be90","cinema_name":"Rochdale","showtimeId":"843-4532","film_id":"HO00001364","cinema_id":"843","film_name":"Fast & Furious 9","date":"2021-08-05","time":"2021-08-05T11:30:00+01:00","is3d":false,"__v":0},{"_id":"6109a61b3501a660f793be91","cinema_name":"Rochdale","showtimeId":"843-4529","film_id":"HO00001364","cinema_id":"843","film_name":"Fast & Furious 9","date":"2021-08-05","time":"2021-08-05T12:00:00+01:00","is3d":false,"__v":0},{"_id":"6109a61b3501a660f793be92","cinema_name":"Rochdale","showtimeId":"843-4546","film_id":"HO00001364","cinema_id":"843","film_name":"Fast & Furious 9","date":"2021-08-05","time":"2021-08-05T12:50:00+01:00","is3d":false,"__v":0},{"_id":"6109a61b3501a660f793be93","cinema_name":"Rochdale","showtimeId":"843-4534","film_id":"HO00001364","cinema_id":"843","film_name":"Fast & Furious 9","date":"2021-08-05","time":"2021-08-05T13:00:00+01:00","is3d":false,"__v":0},{"_id":"6109a61b3501a660f793be94","cinema_name":"Rochdale","showtimeId":"843-4552","film_id":"HO00001364","cinema_id":"843","film_name":"Fast & Furious 9","date":"2021-08-05","time":"2021-08-05T13:10:00+01:00","is3d":false,"__v":0},{"_id":"6109a61b3501a660f793be95","cinema_name":"Rochdale","showtimeId":"843-4548","film_id":"HO00001364","cinema_id":"843","film_name":"Fast & Furious 9","date":"2021-08-05","time":"2021-08-05T13:20:00+01:00","is3d":false,"__v":0},{"_id":"6109a61b3501a660f793be96","cinema_name":"Rochdale","showtimeId":"843-4543","film_id":"HO00001364","cinema_id":"843","film_name":"Fast & Furious 9","date":"2021-08-05","time":"2021-08-05T13:40:00+01:00","is3d":false,"__v":0},{"_id":"6109a61b3501a660f793be97","cinema_name":"Rochdale","showtimeId":"843-4524","film_id":"HO00001364","cinema_id":"843","film_name":"Fast & Furious 9","date":"2021-08-05","time":"2021-08-05T14:00:00+01:00","is3d":false,"__v":0},{"_id":"6109a61b3501a660f793be98","cinema_name":"Rochdale","showtimeId":"843-4541","film_id":"HO00001364","cinema_id":"843","film_name":"Fast & Furious 9","date":"2021-08-05","time":"2021-08-05T14:10:00+01:00","is3d":false,"__v":0},{"_id":"6109a61b3501a660f793be99","cinema_name":"Rochdale","showtimeId":"843-4530","film_id":"HO00001364","cinema_id":"843","film_name":"Fast & Furious 9","date":"2021-08-05","time":"2021-08-05T14:30:00+01:00","is3d":false,"__v":0},{"_id":"6109a61b3501a660f793be9a","cinema_name":"Rochdale","showtimeId":"843-4528","film_id":"HO00001364","cinema_id":"843","film_name":"Fast & Furious 9","date":"2021-08-05","time":"2021-08-05T14:50:00+01:00","is3d":false,"__v":0},{"_id":"6109a61b3501a660f793be9b","cinema_name":"Rochdale","showtimeId":"843-4533","film_id":"HO00001364","cinema_id":"843","film_name":"Fast & Furious 9","date":"2021-08-05","time":"2021-08-05T15:30:00+01:00","is3d":false,"__v":0},{"_id":"6109a61b3501a660f793be9c","cinema_name":"Rochdale","showtimeId":"843-4547","film_id":"HO00001364","cinema_id":"843","film_name":"Fast & Furious 9","date":"2021-08-05","time":"2021-08-05T15:50:00+01:00","is3d":false,"__v":0},{"_id":"6109a61b3501a660f793be9d","cinema_name":"Rochdale","showtimeId":"843-4545","film_id":"HO00001364","cinema_id":"843","film_name":"Fast & Furious 9","date":"2021-08-05","time":"2021-08-05T15:50:00+01:00","is3d":false,"__v":0},{"_id":"6109a61b3501a660f793be9e","cinema_name":"Rochdale","showtimeId":"843-4551","film_id":"HO00001364","cinema_id":"843","film_name":"Fast & Furious 9","date":"2021-08-05","time":"2021-08-05T16:10:00+01:00","is3d":false,"__v":0},{"_id":"6109a61b3501a660f793be9f","cinema_name":"Rochdale","showtimeId":"843-4537","film_id":"HO00001364","cinema_id":"843","film_name":"Fast & Furious 9","date":"2021-08-05","time":"2021-08-05T16:50:00+01:00","is3d":false,"__v":0},{"_id":"6109a61b3501a660f793bea0","cinema_name":"Rochdale","showtimeId":"843-4540","film_id":"HO00001364","cinema_id":"843","film_name":"Fast & Furious 9","date":"2021-08-05","time":"2021-08-05T17:10:00+01:00","is3d":false,"__v":0},{"_id":"6109a61b3501a660f793bea1","cinema_name":"Rochdale","showtimeId":"843-4525","film_id":"HO00001364","cinema_id":"843","film_name":"Fast & Furious 9","date":"2021-08-05","time":"2021-08-05T17:20:00+01:00","is3d":false,"__v":0},{"_id":"6109a61b3501a660f793bea2","cinema_name":"Rochdale","showtimeId":"843-4527","film_id":"HO00001364","cinema_id":"843","film_name":"Fast & Furious 9","date":"2021-08-05","time":"2021-08-05T17:40:00+01:00","is3d":false,"__v":0},{"_id":"6109a61b3501a660f793bea3","cinema_name":"Rochdale","showtimeId":"843-4536","film_id":"HO00001364","cinema_id":"843","film_name":"Fast & Furious 9","date":"2021-08-05","time":"2021-08-05T17:50:00+01:00","is3d":false,"__v":0},{"_id":"6109a61b3501a660f793bea4","cinema_name":"Rochdale","showtimeId":"843-4520","film_id":"HO00001364","cinema_id":"843","film_name":"Fast & Furious 9","date":"2021-08-05","time":"2021-08-05T18:00:00+01:00","is3d":false,"__v":0},{"_id":"6109a61b3501a660f793bea5","cinema_name":"Rochdale","showtimeId":"843-4517","film_id":"HO00001364","cinema_id":"843","film_name":"Fast & Furious 9","date":"2021-08-05","time":"2021-08-05T18:30:00+01:00","is3d":false,"__v":0},{"_id":"6109a61b3501a660f793bea6","cinema_name":"Rochdale","showtimeId":"843-4614","film_id":"HO00001364","cinema_id":"843","film_name":"Fast & Furious 9","date":"2021-08-05","time":"2021-08-05T19:00:00+01:00","is3d":false,"__v":0},{"_id":"6109a61b3501a660f793bea7","cinema_name":"Rochdale","showtimeId":"843-4550","film_id":"HO00001364","cinema_id":"843","film_name":"Fast & Furious 9","date":"2021-08-05","time":"2021-08-05T19:10:00+01:00","is3d":false,"__v":0},{"_id":"6109a61b3501a660f793bea8","cinema_name":"Rochdale","showtimeId":"843-4535","film_id":"HO00001364","cinema_id":"843","film_name":"Fast & Furious 9","date":"2021-08-05","time":"2021-08-05T20:00:00+01:00","is3d":false,"__v":0},{"_id":"6109a61b3501a660f793bea9","cinema_name":"Rochdale","showtimeId":"843-4539","film_id":"HO00001364","cinema_id":"843","film_name":"Fast & Furious 9","date":"2021-08-05","time":"2021-08-05T20:10:00+01:00","is3d":false,"__v":0},{"_id":"6109a61b3501a660f793beaa","cinema_name":"Rochdale","showtimeId":"843-4518","film_id":"HO00001364","cinema_id":"843","film_name":"Fast & Furious 9","date":"2021-08-05","time":"2021-08-05T20:30:00+01:00","is3d":false,"__v":0},{"_id":"6109a61b3501a660f793beab","cinema_name":"Rochdale","showtimeId":"843-4521","film_id":"HO00001364","cinema_id":"843","film_name":"Fast & Furious 9","date":"2021-08-05","time":"2021-08-05T20:40:00+01:00","is3d":false,"__v":0},{"_id":"6109a61b3501a660f793beac","cinema_name":"Rochdale","showtimeId":"843-4519","film_id":"HO00001364","cinema_id":"843","film_name":"Fast & Furious 9","date":"2021-08-05","time":"2021-08-05T20:50:00+01:00","is3d":false,"__v":0},{"_id":"6109a61b3501a660f793bead","cinema_name":"Rochdale","showtimeId":"843-4538","film_id":"HO00001364","cinema_id":"843","film_name":"Fast & Furious 9","date":"2021-08-05","time":"2021-08-05T21:00:00+01:00","is3d":false,"__v":0},{"_id":"6109a61b3501a660f793beae","cinema_name":"Rochdale","showtimeId":"843-4523","film_id":"HO00001364","cinema_id":"843","film_name":"Fast & Furious 9","date":"2021-08-05","time":"2021-08-05T21:20:00+01:00","is3d":false,"__v":0}]}