{"_id":{"film_id":"HO00000369","cinema_id":"530"},"file":[{"_id":"6109a6163501a660f792ed77","cinema_name":"Glasgow Quay","showtimeId":"530-5026","film_id":"HO00000369","cinema_id":"530","film_name":"Jungle Cruise","date":"2021-08-04","time":"2021-08-04T17:00:00+01:00","is3d":false,"__v":0},{"_id":"6109a6163501a660f792ed78","cinema_name":"Glasgow Quay","showtimeId":"530-5033","film_id":"HO00000369","cinema_id":"530","film_name":"Jungle Cruise","date":"2021-08-04","time":"2021-08-04T17:10:00+01:00","is3d":false,"__v":0},{"_id":"6109a6163501a660f792ed79","cinema_name":"Glasgow Quay","showtimeId":"530-5028","film_id":"HO00000369","cinema_id":"530","film_name":"Jungle Cruise","date":"2021-08-04","time":"2021-08-04T17:20:00+01:00","is3d":false,"__v":0},{"_id":"6109a6163501a660f792ed7a","cinema_name":"Glasgow Quay","showtimeId":"530-5030","film_id":"HO00000369","cinema_id":"530","film_name":"Jungle Cruise","date":"2021-08-04","time":"2021-08-04T17:40:00+01:00","is3d":false,"__v":0},{"_id":"6109a6163501a660f792ed7b","cinema_name":"Glasgow Quay","showtimeId":"530-4118","film_id":"HO00000369","cinema_id":"530","film_name":"Jungle Cruise","date":"2021-08-04","time":"2021-08-04T17:50:00+01:00","is3d":false,"__v":0},{"_id":"6109a6163501a660f792ed7c","cinema_name":"Glasgow Quay","showtimeId":"530-5032","film_id":"HO00000369","cinema_id":"530","film_name":"Jungle Cruise","date":"2021-08-04","time":"2021-08-04T18:00:00+01:00","is3d":false,"__v":0},{"_id":"6109a6163501a660f792ed7d","cinema_name":"Glasgow Quay","showtimeId":"530-5036","film_id":"HO00000369","cinema_id":"530","film_name":"Jungle Cruise","date":"2021-08-04","time":"2021-08-04T18:30:00+01:00","is3d":false,"__v":0},{"_id":"6109a6163501a660f792ed7e","cinema_name":"Glasgow Quay","showtimeId":"530-5034","film_id":"HO00000369","cinema_id":"530","film_name":"Jungle Cruise","date":"2021-08-04","time":"2021-08-04T19:30:00+01:00","is3d":false,"__v":0},{"_id":"6109a6163501a660f792ed7f","cinema_name":"Glasgow Quay","showtimeId":"530-5027","film_id":"HO00000369","cinema_id":"530","film_name":"Jungle Cruise","date":"2021-08-04","time":"2021-08-04T20:00:00+01:00","is3d":false,"__v":0},{"_id":"6109a6163501a660f792ed80","cinema_name":"Glasgow Quay","showtimeId":"530-5029","film_id":"HO00000369","cinema_id":"530","film_name":"Jungle Cruise","date":"2021-08-04","time":"2021-08-04T20:15:00+01:00","is3d":false,"__v":0},{"_id":"6109a6163501a660f792ed81","cinema_name":"Glasgow Quay","showtimeId":"530-5039","film_id":"HO00000369","cinema_id":"530","film_name":"Jungle Cruise","date":"2021-08-04","time":"2021-08-04T20:30:00+01:00","is3d":false,"__v":0},{"_id":"6109a6163501a660f792ed82","cinema_name":"Glasgow Quay","showtimeId":"530-5015","film_id":"HO00000369","cinema_id":"530","film_name":"Jungle Cruise","date":"2021-08-04","time":"2021-08-04T20:45:00+01:00","is3d":false,"__v":0},{"_id":"6109a6163501a660f792ed83","cinema_name":"Glasgow Quay","showtimeId":"530-5031","film_id":"HO00000369","cinema_id":"530","film_name":"Jungle Cruise","date":"2021-08-04","time":"2021-08-04T21:00:00+01:00","is3d":false,"__v":0},{"_id":"6109a6163501a660f792ed84","cinema_name":"Glasgow Quay","showtimeId":"530-5037","film_id":"HO00000369","cinema_id":"530","film_name":"Jungle Cruise","date":"2021-08-04","time":"2021-08-04T21:45:00+01:00","is3d":false,"__v":0},{"_id":"6109a6163501a660f792ed85","cinema_name":"Glasgow Quay","showtimeId":"530-5038","film_id":"HO00000369","cinema_id":"530","film_name":"Jungle Cruise","date":"2021-08-04","time":"2021-08-04T22:00:00+01:00","is3d":false,"__v":0},{"_id":"6109a61a3501a660f7939756","cinema_name":"Glasgow Quay","showtimeId":"530-5051","film_id":"HO00000369","cinema_id":"530","film_name":"Jungle Cruise","date":"2021-08-05","time":"2021-08-05T17:00:00+01:00","is3d":false,"__v":0},{"_id":"6109a61a3501a660f7939757","cinema_name":"Glasgow Quay","showtimeId":"530-5044","film_id":"HO00000369","cinema_id":"530","film_name":"Jungle Cruise","date":"2021-08-05","time":"2021-08-05T17:10:00+01:00","is3d":false,"__v":0},{"_id":"6109a61a3501a660f7939758","cinema_name":"Glasgow Quay","showtimeId":"530-5049","film_id":"HO00000369","cinema_id":"530","film_name":"Jungle Cruise","date":"2021-08-05","time":"2021-08-05T17:20:00+01:00","is3d":false,"__v":0},{"_id":"6109a61a3501a660f7939759","cinema_name":"Glasgow Quay","showtimeId":"530-5042","film_id":"HO00000369","cinema_id":"530","film_name":"Jungle Cruise","date":"2021-08-05","time":"2021-08-05T17:30:00+01:00","is3d":false,"__v":0},{"_id":"6109a61a3501a660f793975a","cinema_name":"Glasgow Quay","showtimeId":"530-5047","film_id":"HO00000369","cinema_id":"530","film_name":"Jungle Cruise","date":"2021-08-05","time":"2021-08-05T17:45:00+01:00","is3d":false,"__v":0},{"_id":"6109a61a3501a660f793975b","cinema_name":"Glasgow Quay","showtimeId":"530-5045","film_id":"HO00000369","cinema_id":"530","film_name":"Jungle Cruise","date":"2021-08-05","time":"2021-08-05T18:00:00+01:00","is3d":false,"__v":0},{"_id":"6109a61a3501a660f793975c","cinema_name":"Glasgow Quay","showtimeId":"530-5040","film_id":"HO00000369","cinema_id":"530","film_name":"Jungle Cruise","date":"2021-08-05","time":"2021-08-05T18:30:00+01:00","is3d":false,"__v":0},{"_id":"6109a61a3501a660f793975d","cinema_name":"Glasgow Quay","showtimeId":"530-5043","film_id":"HO00000369","cinema_id":"530","film_name":"Jungle Cruise","date":"2021-08-05","time":"2021-08-05T19:30:00+01:00","is3d":false,"__v":0},{"_id":"6109a61a3501a660f793975e","cinema_name":"Glasgow Quay","showtimeId":"530-5050","film_id":"HO00000369","cinema_id":"530","film_name":"Jungle Cruise","date":"2021-08-05","time":"2021-08-05T20:00:00+01:00","is3d":false,"__v":0},{"_id":"6109a61a3501a660f793975f","cinema_name":"Glasgow Quay","showtimeId":"530-5048","film_id":"HO00000369","cinema_id":"530","film_name":"Jungle Cruise","date":"2021-08-05","time":"2021-08-05T20:15:00+01:00","is3d":false,"__v":0},{"_id":"6109a61a3501a660f7939760","cinema_name":"Glasgow Quay","showtimeId":"530-5054","film_id":"HO00000369","cinema_id":"530","film_name":"Jungle Cruise","date":"2021-08-05","time":"2021-08-05T20:30:00+01:00","is3d":false,"__v":0},{"_id":"6109a61a3501a660f7939761","cinema_name":"Glasgow Quay","showtimeId":"530-5041","film_id":"HO00000369","cinema_id":"530","film_name":"Jungle Cruise","date":"2021-08-05","time":"2021-08-05T20:45:00+01:00","is3d":false,"__v":0},{"_id":"6109a61a3501a660f7939762","cinema_name":"Glasgow Quay","showtimeId":"530-5046","film_id":"HO00000369","cinema_id":"530","film_name":"Jungle Cruise","date":"2021-08-05","time":"2021-08-05T21:00:00+01:00","is3d":false,"__v":0},{"_id":"6109a61a3501a660f7939763","cinema_name":"Glasgow Quay","showtimeId":"530-5052","film_id":"HO00000369","cinema_id":"530","film_name":"Jungle Cruise","date":"2021-08-05","time":"2021-08-05T21:45:00+01:00","is3d":false,"__v":0},{"_id":"6109a61a3501a660f7939764","cinema_name":"Glasgow Quay","showtimeId":"530-5053","film_id":"HO00000369","cinema_id":"530","film_name":"Jungle Cruise","date":"2021-08-05","time":"2021-08-05T22:00:00+01:00","is3d":false,"__v":0},{"_id":"6109a61e3501a660f7943ff1","cinema_name":"Glasgow Quay","showtimeId":"530-5144","film_id":"HO00000369","cinema_id":"530","film_name":"Jungle Cruise","date":"2021-08-06","time":"2021-08-06T17:00:00+01:00","is3d":false,"__v":0},{"_id":"6109a61e3501a660f7943ff2","cinema_name":"Glasgow Quay","showtimeId":"530-5059","film_id":"HO00000369","cinema_id":"530","film_name":"Jungle Cruise","date":"2021-08-06","time":"2021-08-06T17:10:00+01:00","is3d":false,"__v":0},{"_id":"6109a61e3501a660f7943ff3","cinema_name":"Glasgow Quay","showtimeId":"530-5145","film_id":"HO00000369","cinema_id":"530","film_name":"Jungle Cruise","date":"2021-08-06","time":"2021-08-06T17:20:00+01:00","is3d":false,"__v":0},{"_id":"6109a61e3501a660f7943ff4","cinema_name":"Glasgow Quay","showtimeId":"530-5152","film_id":"HO00000369","cinema_id":"530","film_name":"Jungle Cruise","date":"2021-08-06","time":"2021-08-06T17:30:00+01:00","is3d":false,"__v":0},{"_id":"6109a61e3501a660f7943ff5","cinema_name":"Glasgow Quay","showtimeId":"530-5157","film_id":"HO00000369","cinema_id":"530","film_name":"Jungle Cruise","date":"2021-08-06","time":"2021-08-06T17:40:00+01:00","is3d":false,"__v":0},{"_id":"6109a61e3501a660f7943ff6","cinema_name":"Glasgow Quay","showtimeId":"530-5062","film_id":"HO00000369","cinema_id":"530","film_name":"Jungle Cruise","date":"2021-08-06","time":"2021-08-06T17:50:00+01:00","is3d":false,"__v":0},{"_id":"6109a61e3501a660f7943ff7","cinema_name":"Glasgow Quay","showtimeId":"530-5061","film_id":"HO00000369","cinema_id":"530","film_name":"Jungle Cruise","date":"2021-08-06","time":"2021-08-06T18:00:00+01:00","is3d":false,"__v":0},{"_id":"6109a61e3501a660f7943ff8","cinema_name":"Glasgow Quay","showtimeId":"530-5060","film_id":"HO00000369","cinema_id":"530","film_name":"Jungle Cruise","date":"2021-08-06","time":"2021-08-06T18:10:00+01:00","is3d":false,"__v":0},{"_id":"6109a61e3501a660f7943ff9","cinema_name":"Glasgow Quay","showtimeId":"530-5147","film_id":"HO00000369","cinema_id":"530","film_name":"Jungle Cruise","date":"2021-08-06","time":"2021-08-06T18:20:00+01:00","is3d":false,"__v":0},{"_id":"6109a61e3501a660f7943ffa","cinema_name":"Glasgow Quay","showtimeId":"530-5141","film_id":"HO00000369","cinema_id":"530","film_name":"Jungle Cruise","date":"2021-08-06","time":"2021-08-06T18:50:00+01:00","is3d":false,"__v":0},{"_id":"6109a61e3501a660f7943ffb","cinema_name":"Glasgow Quay","showtimeId":"530-5155","film_id":"HO00000369","cinema_id":"530","film_name":"Jungle Cruise","date":"2021-08-06","time":"2021-08-06T19:10:00+01:00","is3d":false,"__v":0},{"_id":"6109a61e3501a660f7943ffc","cinema_name":"Glasgow Quay","showtimeId":"530-5146","film_id":"HO00000369","cinema_id":"530","film_name":"Jungle Cruise","date":"2021-08-06","time":"2021-08-06T19:20:00+01:00","is3d":false,"__v":0},{"_id":"6109a61e3501a660f7943ffd","cinema_name":"Glasgow Quay","showtimeId":"530-5143","film_id":"HO00000369","cinema_id":"530","film_name":"Jungle Cruise","date":"2021-08-06","time":"2021-08-06T19:50:00+01:00","is3d":false,"__v":0},{"_id":"6109a61e3501a660f7943ffe","cinema_name":"Glasgow Quay","showtimeId":"530-5156","film_id":"HO00000369","cinema_id":"530","film_name":"Jungle Cruise","date":"2021-08-06","time":"2021-08-06T20:00:00+01:00","is3d":false,"__v":0},{"_id":"6109a61e3501a660f7943fff","cinema_name":"Glasgow Quay","showtimeId":"530-5063","film_id":"HO00000369","cinema_id":"530","film_name":"Jungle Cruise","date":"2021-08-06","time":"2021-08-06T20:10:00+01:00","is3d":false,"__v":0},{"_id":"6109a61e3501a660f7944000","cinema_name":"Glasgow Quay","showtimeId":"530-5154","film_id":"HO00000369","cinema_id":"530","film_name":"Jungle Cruise","date":"2021-08-06","time":"2021-08-06T20:20:00+01:00","is3d":false,"__v":0},{"_id":"6109a61e3501a660f7944001","cinema_name":"Glasgow Quay","showtimeId":"530-5064","film_id":"HO00000369","cinema_id":"530","film_name":"Jungle Cruise","date":"2021-08-06","time":"2021-08-06T20:40:00+01:00","is3d":false,"__v":0},{"_id":"6109a61e3501a660f7944002","cinema_name":"Glasgow Quay","showtimeId":"530-5153","film_id":"HO00000369","cinema_id":"530","film_name":"Jungle Cruise","date":"2021-08-06","time":"2021-08-06T20:50:00+01:00","is3d":false,"__v":0},{"_id":"6109a61e3501a660f7944003","cinema_name":"Glasgow Quay","showtimeId":"530-5066","film_id":"HO00000369","cinema_id":"530","film_name":"Jungle Cruise","date":"2021-08-06","time":"2021-08-06T21:00:00+01:00","is3d":false,"__v":0},{"_id":"6109a61e3501a660f7944004","cinema_name":"Glasgow Quay","showtimeId":"530-5150","film_id":"HO00000369","cinema_id":"530","film_name":"Jungle Cruise","date":"2021-08-06","time":"2021-08-06T21:20:00+01:00","is3d":false,"__v":0},{"_id":"6109a61e3501a660f7944005","cinema_name":"Glasgow Quay","showtimeId":"530-5065","film_id":"HO00000369","cinema_id":"530","film_name":"Jungle Cruise","date":"2021-08-06","time":"2021-08-06T21:30:00+01:00","is3d":false,"__v":0},{"_id":"6109a61e3501a660f7944006","cinema_name":"Glasgow Quay","showtimeId":"530-5142","film_id":"HO00000369","cinema_id":"530","film_name":"Jungle Cruise","date":"2021-08-06","time":"2021-08-06T22:00:00+01:00","is3d":false,"__v":0},{"_id":"6109a61e3501a660f7944007","cinema_name":"Glasgow Quay","showtimeId":"530-5149","film_id":"HO00000369","cinema_id":"530","film_name":"Jungle Cruise","date":"2021-08-06","time":"2021-08-06T22:20:00+01:00","is3d":false,"__v":0},{"_id":"6109a61e3501a660f7944008","cinema_name":"Glasgow Quay","showtimeId":"530-5158","film_id":"HO00000369","cinema_id":"530","film_name":"Jungle Cruise","date":"2021-08-06","time":"2021-08-06T22:30:00+01:00","is3d":false,"__v":0},{"_id":"6109a61e3501a660f7944009","cinema_name":"Glasgow Quay","showtimeId":"530-5159","film_id":"HO00000369","cinema_id":"530","film_name":"Jungle Cruise","date":"2021-08-06","time":"2021-08-06T22:50:00+01:00","is3d":false,"__v":0},{"_id":"6109a61e3501a660f794400a","cinema_name":"Glasgow Quay","showtimeId":"530-5148","film_id":"HO00000369","cinema_id":"530","film_name":"Jungle Cruise","date":"2021-08-06","time":"2021-08-06T23:00:00+01:00","is3d":false,"__v":0},{"_id":"6109a61e3501a660f794400b","cinema_name":"Glasgow Quay","showtimeId":"530-5151","film_id":"HO00000369","cinema_id":"530","film_name":"Jungle Cruise","date":"2021-08-06","time":"2021-08-06T23:10:00+01:00","is3d":false,"__v":0}]}