{"_id":{"film_id":"HO00001358","cinema_id":"851"},"file":[{"_id":"6109a6203501a660f79482c5","cinema_name":"Oldham","showtimeId":"851-2441","film_id":"HO00001358","cinema_id":"851","film_name":"Peter Rabbit 2","date":"2021-08-06","time":"2021-08-06T10:00:00+01:00","is3d":false,"__v":0},{"_id":"6109a6203501a660f79482c6","cinema_name":"Oldham","showtimeId":"851-2432","film_id":"HO00001358","cinema_id":"851","film_name":"Peter Rabbit 2","date":"2021-08-06","time":"2021-08-06T10:20:00+01:00","is3d":false,"__v":0},{"_id":"6109a6203501a660f79482c7","cinema_name":"Oldham","showtimeId":"851-2409","film_id":"HO00001358","cinema_id":"851","film_name":"Peter Rabbit 2","date":"2021-08-06","time":"2021-08-06T10:30:00+01:00","is3d":false,"__v":0},{"_id":"6109a6203501a660f79482c8","cinema_name":"Oldham","showtimeId":"851-2426","film_id":"HO00001358","cinema_id":"851","film_name":"Peter Rabbit 2","date":"2021-08-06","time":"2021-08-06T10:50:00+01:00","is3d":false,"__v":0},{"_id":"6109a6203501a660f79482c9","cinema_name":"Oldham","showtimeId":"851-2371","film_id":"HO00001358","cinema_id":"851","film_name":"Peter Rabbit 2","date":"2021-08-06","time":"2021-08-06T11:10:00+01:00","is3d":false,"__v":0},{"_id":"6109a6203501a660f79482ca","cinema_name":"Oldham","showtimeId":"851-2423","film_id":"HO00001358","cinema_id":"851","film_name":"Peter Rabbit 2","date":"2021-08-06","time":"2021-08-06T11:50:00+01:00","is3d":false,"__v":0},{"_id":"6109a6203501a660f79482cb","cinema_name":"Oldham","showtimeId":"851-2413","film_id":"HO00001358","cinema_id":"851","film_name":"Peter Rabbit 2","date":"2021-08-06","time":"2021-08-06T12:00:00+01:00","is3d":false,"__v":0},{"_id":"6109a6203501a660f79482cc","cinema_name":"Oldham","showtimeId":"851-2433","film_id":"HO00001358","cinema_id":"851","film_name":"Peter Rabbit 2","date":"2021-08-06","time":"2021-08-06T12:40:00+01:00","is3d":false,"__v":0},{"_id":"6109a6203501a660f79482cd","cinema_name":"Oldham","showtimeId":"851-2410","film_id":"HO00001358","cinema_id":"851","film_name":"Peter Rabbit 2","date":"2021-08-06","time":"2021-08-06T13:00:00+01:00","is3d":false,"__v":0},{"_id":"6109a6203501a660f79482ce","cinema_name":"Oldham","showtimeId":"851-2408","film_id":"HO00001358","cinema_id":"851","film_name":"Peter Rabbit 2","date":"2021-08-06","time":"2021-08-06T13:10:00+01:00","is3d":false,"__v":0},{"_id":"6109a6203501a660f79482cf","cinema_name":"Oldham","showtimeId":"851-2427","film_id":"HO00001358","cinema_id":"851","film_name":"Peter Rabbit 2","date":"2021-08-06","time":"2021-08-06T13:50:00+01:00","is3d":false,"__v":0},{"_id":"6109a6203501a660f79482d0","cinema_name":"Oldham","showtimeId":"851-2372","film_id":"HO00001358","cinema_id":"851","film_name":"Peter Rabbit 2","date":"2021-08-06","time":"2021-08-06T14:10:00+01:00","is3d":false,"__v":0},{"_id":"6109a6203501a660f79482d1","cinema_name":"Oldham","showtimeId":"851-2383","film_id":"HO00001358","cinema_id":"851","film_name":"Peter Rabbit 2","date":"2021-08-06","time":"2021-08-06T14:30:00+01:00","is3d":false,"__v":0},{"_id":"6109a6203501a660f79482d2","cinema_name":"Oldham","showtimeId":"851-2442","film_id":"HO00001358","cinema_id":"851","film_name":"Peter Rabbit 2","date":"2021-08-06","time":"2021-08-06T14:50:00+01:00","is3d":false,"__v":0},{"_id":"6109a6203501a660f79482d3","cinema_name":"Oldham","showtimeId":"851-2434","film_id":"HO00001358","cinema_id":"851","film_name":"Peter Rabbit 2","date":"2021-08-06","time":"2021-08-06T15:00:00+01:00","is3d":false,"__v":0},{"_id":"6109a6203501a660f79482d4","cinema_name":"Oldham","showtimeId":"851-2411","film_id":"HO00001358","cinema_id":"851","film_name":"Peter Rabbit 2","date":"2021-08-06","time":"2021-08-06T15:30:00+01:00","is3d":false,"__v":0},{"_id":"6109a6203501a660f79482d5","cinema_name":"Oldham","showtimeId":"851-2407","film_id":"HO00001358","cinema_id":"851","film_name":"Peter Rabbit 2","date":"2021-08-06","time":"2021-08-06T16:10:00+01:00","is3d":false,"__v":0},{"_id":"6109a6203501a660f79482d6","cinema_name":"Oldham","showtimeId":"851-2428","film_id":"HO00001358","cinema_id":"851","film_name":"Peter Rabbit 2","date":"2021-08-06","time":"2021-08-06T16:50:00+01:00","is3d":false,"__v":0},{"_id":"6109a6203501a660f79482d7","cinema_name":"Oldham","showtimeId":"851-2373","film_id":"HO00001358","cinema_id":"851","film_name":"Peter Rabbit 2","date":"2021-08-06","time":"2021-08-06T17:10:00+01:00","is3d":false,"__v":0},{"_id":"6109a6203501a660f79482d8","cinema_name":"Oldham","showtimeId":"851-2392","film_id":"HO00001358","cinema_id":"851","film_name":"Peter Rabbit 2","date":"2021-08-06","time":"2021-08-06T17:20:00+01:00","is3d":false,"__v":0},{"_id":"6109a6203501a660f79482d9","cinema_name":"Oldham","showtimeId":"851-2384","film_id":"HO00001358","cinema_id":"851","film_name":"Peter Rabbit 2","date":"2021-08-06","time":"2021-08-06T17:40:00+01:00","is3d":false,"__v":0},{"_id":"6109a6203501a660f79482da","cinema_name":"Oldham","showtimeId":"851-2398","film_id":"HO00001358","cinema_id":"851","film_name":"Peter Rabbit 2","date":"2021-08-06","time":"2021-08-06T17:50:00+01:00","is3d":false,"__v":0},{"_id":"6109a6203501a660f79482db","cinema_name":"Oldham","showtimeId":"851-2412","film_id":"HO00001358","cinema_id":"851","film_name":"Peter Rabbit 2","date":"2021-08-06","time":"2021-08-06T18:00:00+01:00","is3d":false,"__v":0},{"_id":"6109a6203501a660f79482dc","cinema_name":"Oldham","showtimeId":"851-2406","film_id":"HO00001358","cinema_id":"851","film_name":"Peter Rabbit 2","date":"2021-08-06","time":"2021-08-06T19:10:00+01:00","is3d":false,"__v":0},{"_id":"6109a6203501a660f79482dd","cinema_name":"Oldham","showtimeId":"851-2418","film_id":"HO00001358","cinema_id":"851","film_name":"Peter Rabbit 2","date":"2021-08-06","time":"2021-08-06T19:50:00+01:00","is3d":false,"__v":0},{"_id":"6109a6203501a660f79482de","cinema_name":"Oldham","showtimeId":"851-2374","film_id":"HO00001358","cinema_id":"851","film_name":"Peter Rabbit 2","date":"2021-08-06","time":"2021-08-06T20:10:00+01:00","is3d":false,"__v":0},{"_id":"6109a6203501a660f79482df","cinema_name":"Oldham","showtimeId":"851-2399","film_id":"HO00001358","cinema_id":"851","film_name":"Peter Rabbit 2","date":"2021-08-06","time":"2021-08-06T20:30:00+01:00","is3d":false,"__v":0},{"_id":"6109a6203501a660f79482e0","cinema_name":"Oldham","showtimeId":"851-2393","film_id":"HO00001358","cinema_id":"851","film_name":"Peter Rabbit 2","date":"2021-08-06","time":"2021-08-06T20:40:00+01:00","is3d":false,"__v":0},{"_id":"6109a6203501a660f79482e1","cinema_name":"Oldham","showtimeId":"851-2385","film_id":"HO00001358","cinema_id":"851","film_name":"Peter Rabbit 2","date":"2021-08-06","time":"2021-08-06T20:50:00+01:00","is3d":false,"__v":0},{"_id":"6109a6203501a660f79482e2","cinema_name":"Oldham","showtimeId":"851-2579","film_id":"HO00001358","cinema_id":"851","film_name":"Peter Rabbit 2","date":"2021-08-06","time":"2021-08-06T21:00:00+01:00","is3d":false,"__v":0}]}